WinDbg_Copilot/WinDbg_Copilot.py
WinDbg_Copilot/WinDbg_Copilot_Console.py
WinDbg_Copilot/WinDbg_Copilot_GUI.py
WinDbg_Copilot/__init__.py
WinDbg_Copilot/config.ini
WinDbg_Copilot/thumbnail.ico
WinDbg_Copilot/version.py
WinDbg_Copilot-1.0.62.dist-info/LICENSE.txt
WinDbg_Copilot-1.0.62.dist-info/METADATA
WinDbg_Copilot-1.0.62.dist-info/WHEEL
WinDbg_Copilot-1.0.62.dist-info/entry_points.txt
WinDbg_Copilot-1.0.62.dist-info/top_level.txt
WinDbg_Copilot-1.0.62.dist-info/RECORD
