Metadata-Version: 2.1
Name: WinDbg-Copilot
Version: 1.0.62
Summary: "WinDbg Copilot is a ChatGPT powered AI assistant integrated with WinDbg. It analyzes the output of the commands, and provides guidance to solve the stated problem."
Home-page: https://github.com/suannai231/WinDbg_Copilot
Download-URL: 
Author: Jack Yin
Author-email: suannai231@gmail.com
License: MIT
Keywords: WinDbg,Copilot,chatgpt,openai
Classifier: Development Status :: 5 - Production/Stable
Classifier: Intended Audience :: Developers
Classifier: Topic :: Software Development :: Build Tools
Classifier: License :: OSI Approved :: MIT License
Classifier: Programming Language :: Python
Classifier: Programming Language :: Python :: 3.8
Classifier: Programming Language :: Python :: 3.9
Classifier: Programming Language :: Python :: 3.10
Classifier: Programming Language :: Python :: 3.11
Requires-Python: <3.12,>=3.9
License-File: LICENSE.txt
Requires-Dist: openai (>=0.27.2)
Requires-Dist: tiktoken (>=0.4.0)
